{
  "id": "gid://shopify/Cart/Z2NwLXVzLXdlc3QxOjAxSkJDSEZYMTYzTVE4MDdZTldGOUI1NTBW?key=32b03f7a4af0d20b6f71e6acdb7f8b50",
  "createdAt": "2024-10-29T16:24:38Z",
  "updatedAt": "2024-10-29T16:24:38Z",
  "lines": {
    "pageInfo": {
      "hasNextPage": false,
      "hasPreviousPage": false
    },
    "edges": [
      {
        "node": {
          "id": "gid://shopify/CartLine/194b09cb-98fb-4275-b3bb-a8db42ceaf47?cart=Z2NwLXVzLXdlc3QxOjAxSkJDSEZYMTYzTVE4MDdZTldGOUI1NTBW",
          "merchandise": {
            "id": "gid://shopify/ProductVariant/48535896555542",
            "title": "Default Title",
            "image": {
              "id": "gid://shopify/ProductImage/45559092609046",
              "src": "https://cdn.shopify.com/s/files/1/0601/8783/6438/files/LTYyNDAuanBlZw.jpg?v=1724460042",
              "altText": "bay40v_0_Efterklang - Tripper",
              "width": 300,
              "height": 300
            },
            "product": {
              "id": "gid://shopify/Product/9899493589014",
              "handle": "efterklang-tripper",
              "title": "Efterklang - Tripper"
            },
            "weight": 460,
            "available": true,
            "sku": "",
            "selectedOptions": [
              {
                "name": "Title",
                "value": "Default Title"
              }
            ],
            "unitPriceMeasurement": {
              "measuredType": null,
              "quantityUnit": null,
              "quantityValue": 0,
              "referenceUnit": null,
              "referenceValue": 0
            }
          },
          "quantity": 1,
          "attributes": [],
          "cost": {
            "totalAmount": {
              "amount": "70.0",
              "currencyCode": "USD"
            },
            "subtotalAmount": {
              "amount": "70.0",
              "currencyCode": "USD"
            },
            "amountPerQuantity": {
              "amount": "70.0",
              "currencyCode": "USD"
            },
            "compareAtAmountPerQuantity": null
          },
          "discountAllocations": [],
          "sellingPlanAllocation": null
        }
      },
      {
        "node": {
          "id": "gid://shopify/CartLine/10477616-610b-4a23-91f6-39ae6a6cc523?cart=Z2NwLXVzLXdlc3QxOjAxSkJDSEZYMTYzTVE4MDdZTldGOUI1NTBW",
          "merchandise": {
            "id": "gid://shopify/ProductVariant/48535896522774",
            "title": "Default Title",
            "image": {
              "id": "gid://shopify/ProductImage/45559092281366",
              "src": "https://cdn.shopify.com/s/files/1/0601/8783/6438/files/NTMtOTAxNy5qcGVn.jpg?v=1724459712",
              "altText": "pf006_0_Alex Kassian - Strings Of Eden ",
              "width": 500,
              "height": 500
            },
            "product": {
              "id": "gid://shopify/Product/9899493556246",
              "handle": "alex-kassian-strings-of-eden",
              "title": "Alex Kassian - Strings Of Eden"
            },
            "weight": 0,
            "available": true,
            "sku": "",
            "selectedOptions": [
              {
                "name": "Title",
                "value": "Default Title"
              }
            ],
            "unitPriceMeasurement": {
              "measuredType": null,
              "quantityUnit": null,
              "quantityValue": 0,
              "referenceUnit": null,
              "referenceValue": 0
            }
          },
          "quantity": 1,
          "attributes": [],
          "cost": {
            "totalAmount": {
              "amount": "200.0",
              "currencyCode": "USD"
            },
            "subtotalAmount": {
              "amount": "200.0",
              "currencyCode": "USD"
            },
            "amountPerQuantity": {
              "amount": "200.0",
              "currencyCode": "USD"
            },
            "compareAtAmountPerQuantity": null
          },
          "discountAllocations": [],
          "sellingPlanAllocation": null
        }
      }
    ]
  },
  "attributes": [],
  "cost": {
    "totalAmount": {
      "amount": "270.0",
      "currencyCode": "USD"
    },
    "subtotalAmount": {
      "amount": "270.0",
      "currencyCode": "USD"
    },
    "totalTaxAmount": null,
    "totalDutyAmount": null
  },
  "checkoutUrl": "https://mycrate.2ndgentrecords.com/cart/c/Z2NwLXVzLXdlc3QxOjAxSkJDSEZYMTYzTVE4MDdZTldGOUI1NTBW?key=32b03f7a4af0d20b6f71e6acdb7f8b50",
  "discountCodes": [],
  "discountAllocations": [],
  "buyerIdentity": {
    "countryCode": "US",
    "preferences": null,
    "email": null,
    "phone": null,
    "customer": null,
    "deliveryAddressPreferences": []
  },
  "deliveryGroups": {
    "pageInfo": {
      "hasNextPage": false,
      "hasPreviousPage": false
    },
    "edges": []
  },
  "appliedGiftCards": [],
  "note": ""
}
